<?xml version="1.0" ?><annotation>
	<folder>JPEGImages</folder>
	<filename>05_10_18.xml</filename>
	<path>VOCdevkit/VOC2012/JPEGImages/05_10_18.xml</path>
	<source>
		<database>Unknown</database>
	</source>
	<size>
		<width>800</width>
		<height>800</height>
		<depth>1</depth>
	</size>
	<segmented>0</segmented>
	<object>
		<name>ship</name>
		<pose>Unspecified</pose>
		<truncated>0</truncated>
		<difficult>0</difficult>
		<bndbox>
			<xmin>342</xmin>
			<ymin>198</ymin>
			<xmax>352</xmax>
			<ymax>214</ymax>
		</bndbox>
	</object>
	<object>
		<name>ship</name>
		<pose>Unspecified</pose>
		<truncated>1</truncated>
		<difficult>0</difficult>
		<bndbox>
			<xmin>581</xmin>
			<ymin>1</ymin>
			<xmax>633</xmax>
			<ymax>50</ymax>
		</bndbox>
	</object>
	<object>
		<name>ship</name>
		<pose>Unspecified</pose>
		<truncated>0</truncated>
		<difficult>0</difficult>
		<bndbox>
			<xmin>432</xmin>
			<ymin>166</ymin>
			<xmax>450</xmax>
			<ymax>189</ymax>
		</bndbox>
	</object>
	<object>
		<name>ship</name>
		<pose>Unspecified</pose>
		<truncated>0</truncated>
		<difficult>0</difficult>
		<bndbox>
			<xmin>596</xmin>
			<ymin>148</ymin>
			<xmax>627</xmax>
			<ymax>176</ymax>
		</bndbox>
	</object>
	<object>
		<name>ship</name>
		<pose>Unspecified</pose>
		<truncated>0</truncated>
		<difficult>0</difficult>
		<bndbox>
			<xmin>421</xmin>
			<ymin>225</ymin>
			<xmax>431</xmax>
			<ymax>239</ymax>
		</bndbox>
	</object>
	<object>
		<name>ship</name>
		<pose>Unspecified</pose>
		<truncated>0</truncated>
		<difficult>0</difficult>
		<bndbox>
			<xmin>469</xmin>
			<ymin>252</ymin>
			<xmax>478</xmax>
			<ymax>265</ymax>
		</bndbox>
	</object>
	<object>
		<name>ship</name>
		<pose>Unspecified</pose>
		<truncated>0</truncated>
		<difficult>0</difficult>
		<bndbox>
			<xmin>446</xmin>
			<ymin>310</ymin>
			<xmax>469</xmax>
			<ymax>328</ymax>
		</bndbox>
	</object>
	<object>
		<name>ship</name>
		<pose>Unspecified</pose>
		<truncated>0</truncated>
		<difficult>0</difficult>
		<bndbox>
			<xmin>442</xmin>
			<ymin>381</ymin>
			<xmax>505</xmax>
			<ymax>466</ymax>
		</bndbox>
	</object>
	<object>
		<name>ship</name>
		<pose>Unspecified</pose>
		<truncated>0</truncated>
		<difficult>0</difficult>
		<bndbox>
			<xmin>657</xmin>
			<ymin>222</ymin>
			<xmax>682</xmax>
			<ymax>251</ymax>
		</bndbox>
	</object>
	<object>
		<name>ship</name>
		<pose>Unspecified</pose>
		<truncated>0</truncated>
		<difficult>0</difficult>
		<bndbox>
			<xmin>609</xmin>
			<ymin>471</ymin>
			<xmax>628</xmax>
			<ymax>495</ymax>
		</bndbox>
	</object>
	<object>
		<name>ship</name>
		<pose>Unspecified</pose>
		<truncated>0</truncated>
		<difficult>0</difficult>
		<bndbox>
			<xmin>707</xmin>
			<ymin>430</ymin>
			<xmax>755</xmax>
			<ymax>483</ymax>
		</bndbox>
	</object>
	<object>
		<name>ship</name>
		<pose>Unspecified</pose>
		<truncated>0</truncated>
		<difficult>0</difficult>
		<bndbox>
			<xmin>560</xmin>
			<ymin>661</ymin>
			<xmax>606</xmax>
			<ymax>702</ymax>
		</bndbox>
	</object>
	<object>
		<name>ship</name>
		<pose>Unspecified</pose>
		<truncated>0</truncated>
		<difficult>0</difficult>
		<bndbox>
			<xmin>659</xmin>
			<ymin>676</ymin>
			<xmax>707</xmax>
			<ymax>720</ymax>
		</bndbox>
	</object>
	<object>
		<name>ship</name>
		<pose>Unspecified</pose>
		<truncated>1</truncated>
		<difficult>0</difficult>
		<bndbox>
			<xmin>727</xmin>
			<ymin>775</ymin>
			<xmax>754</xmax>
			<ymax>800</ymax>
		</bndbox>
	</object>
	<object>
		<name>ship</name>
		<pose>Unspecified</pose>
		<truncated>1</truncated>
		<difficult>0</difficult>
		<bndbox>
			<xmin>772</xmin>
			<ymin>711</ymin>
			<xmax>800</xmax>
			<ymax>743</ymax>
		</bndbox>
	</object>
</annotation>