<?xml version="1.0" ?><annotation>
	<folder>JPEGImages</folder>
	<filename>11_7_25.xml</filename>
	<path>VOCdevkit/VOC2012/JPEGImages/11_7_25.xml</path>
	<source>
		<database>Unknown</database>
	</source>
	<size>
		<width>800</width>
		<height>800</height>
		<depth>1</depth>
	</size>
	<segmented>0</segmented>
	<object>
		<name>ship</name>
		<pose>Unspecified</pose>
		<truncated>0</truncated>
		<difficult>0</difficult>
		<bndbox>
			<xmin>502</xmin>
			<ymin>636</ymin>
			<xmax>547</xmax>
			<ymax>688</ymax>
		</bndbox>
	</object>
</annotation>