<?xml version="1.0" ?><annotation>
	<folder>JPEGImages</folder>
	<filename>12_11_23.xml</filename>
	<path>VOCdevkit/VOC2012/JPEGImages/12_11_23.xml</path>
	<source>
		<database>Unknown</database>
	</source>
	<size>
		<width>800</width>
		<height>800</height>
		<depth>1</depth>
	</size>
	<segmented>0</segmented>
	<object>
		<name>ship</name>
		<pose>Unspecified</pose>
		<truncated>0</truncated>
		<difficult>0</difficult>
		<bndbox>
			<xmin>399</xmin>
			<ymin>746</ymin>
			<xmax>414</xmax>
			<ymax>777</ymax>
		</bndbox>
	</object>
	<object>
		<name>ship</name>
		<pose>Unspecified</pose>
		<truncated>0</truncated>
		<difficult>0</difficult>
		<bndbox>
			<xmin>768</xmin>
			<ymin>589</ymin>
			<xmax>785</xmax>
			<ymax>625</ymax>
		</bndbox>
	</object>
	<object>
		<name>ship</name>
		<pose>Unspecified</pose>
		<truncated>0</truncated>
		<difficult>0</difficult>
		<bndbox>
			<xmin>748</xmin>
			<ymin>730</ymin>
			<xmax>766</xmax>
			<ymax>750</ymax>
		</bndbox>
	</object>
</annotation>