<?xml version="1.0" ?><annotation>
	<folder>JPEGImages</folder>
	<filename>13_15_6.xml</filename>
	<path>VOCdevkit/VOC2012/JPEGImages/13_15_6.xml</path>
	<source>
		<database>Unknown</database>
	</source>
	<size>
		<width>800</width>
		<height>800</height>
		<depth>1</depth>
	</size>
	<segmented>0</segmented>
	<object>
		<name>ship</name>
		<pose>Unspecified</pose>
		<truncated>0</truncated>
		<difficult>0</difficult>
		<bndbox>
			<xmin>388</xmin>
			<ymin>93</ymin>
			<xmax>411</xmax>
			<ymax>108</ymax>
		</bndbox>
	</object>
	<object>
		<name>ship</name>
		<pose>Unspecified</pose>
		<truncated>0</truncated>
		<difficult>0</difficult>
		<bndbox>
			<xmin>268</xmin>
			<ymin>288</ymin>
			<xmax>280</xmax>
			<ymax>307</ymax>
		</bndbox>
	</object>
	<object>
		<name>ship</name>
		<pose>Unspecified</pose>
		<truncated>0</truncated>
		<difficult>0</difficult>
		<bndbox>
			<xmin>292</xmin>
			<ymin>271</ymin>
			<xmax>320</xmax>
			<ymax>288</ymax>
		</bndbox>
	</object>
	<object>
		<name>ship</name>
		<pose>Unspecified</pose>
		<truncated>0</truncated>
		<difficult>0</difficult>
		<bndbox>
			<xmin>391</xmin>
			<ymin>286</ymin>
			<xmax>406</xmax>
			<ymax>294</ymax>
		</bndbox>
	</object>
	<object>
		<name>ship</name>
		<pose>Unspecified</pose>
		<truncated>0</truncated>
		<difficult>0</difficult>
		<bndbox>
			<xmin>440</xmin>
			<ymin>387</ymin>
			<xmax>463</xmax>
			<ymax>405</ymax>
		</bndbox>
	</object>
</annotation>